Metadata-Version: 1.1
Name: django-pagemore
Version: 0.1.0
Summary: KISS approach to a "Load more" style AJAX paginator.
Home-page: http://github.com/pennersr/django-pagemore
Author: Raymond Penners
Author-email: raymond.penners@intenct.nl
License: UNKNOWN
Keywords: django pagination paginator ajax
Platform: UNKNOWN
Classifier: Development Status :: 4 - Beta
Classifier: Intended Audience :: Developers
Classifier: Topic :: Software Development :: Libraries :: Python Modules
Classifier: Environment :: Web Environment
Classifier: Topic :: Internet
Classifier: Operating System :: OS Independent
Classifier: Programming Language :: Python
Classifier: Framework :: Django
